tank/__init__.py
tank-0.1.0.dist-info/METADATA
tank-0.1.0.dist-info/WHEEL
tank-0.1.0.dist-info/top_level.txt
tank-0.1.0.dist-info/RECORD
