Metadata-Version: 2.1
Name: tank
Version: 0.1.0
Summary: A collection of useful functions/classes for data analysis and ML.
Home-page: http://pypi.python.org/pypi/tank/
Author: William Shiao
Author-email: willshiao@gmail.com
License: LICENSE
Platform: UNKNOWN
